tesseract_idx/__init__.py
tesseract_idx/config.py
tesseract_idx/main.py
sourav_tesseract-0.1.12.dist-info/LICENSE
sourav_tesseract-0.1.12.dist-info/METADATA
sourav_tesseract-0.1.12.dist-info/WHEEL
sourav_tesseract-0.1.12.dist-info/top_level.txt
sourav_tesseract-0.1.12.dist-info/RECORD
