Metadata-Version: 2.1
Name: sourav-tesseract
Version: 0.1.12
Summary: Input Adaptor to verify file extension
Author: Crossml
Author-email: sourav@crossml.com
License: MIT
Keywords: Input-adaptor,Adaptor,DataAdaptor
Platform: UNKNOWN
Requires-Python: >=3
License-File: LICENSE
Requires-Dist: pytesseract
Requires-Dist: pdf2image
Requires-Dist: boto3
